[{"category":"Misc","type":"single","joke":"Una ardilla le pregunta a otra que quiere ser cuando grande, la otra ardilla de responde \u0022Ardila L\u00FClle\u0022.","id":0},{"category":"Programming","type":"single","joke":"No te despedir\u00E1n del trabajo, si nunca comentas tu c\u00F3digo y adem\u00E1s eres el \u00FAnico que sabe c\u00F3mo funciona","id":3},{"category":"Programming","type":"single","joke":"S\u00F3lo hay 10 tipos de personas en este mundo, las que entienden binario y las que no.","id":5}]